cpymadtools/__init__.py
cpymadtools/_version.py
cpymadtools/constants.py
cpymadtools/coupling.py
cpymadtools/matching.py
cpymadtools/ptc.py
cpymadtools/track.py
cpymadtools/tune.py
cpymadtools/twiss.py
cpymadtools/utils.py
cpymadtools/lhc/__init__.py
cpymadtools/lhc/_coupling.py
cpymadtools/lhc/_elements.py
cpymadtools/lhc/_errors.py
cpymadtools/lhc/_misc.py
cpymadtools/lhc/_powering.py
cpymadtools/lhc/_queries.py
cpymadtools/lhc/_routines.py
cpymadtools/lhc/_setup.py
cpymadtools/lhc/_twiss.py
cpymadtools-1.1.0.dist-info/METADATA
cpymadtools-1.1.0.dist-info/WHEEL
cpymadtools-1.1.0.dist-info/licenses/LICENSE
cpymadtools-1.1.0.dist-info/RECORD
